Workbook

Sheet PATIENTS
A1: Customer's Data
A2: Bio data
A3: patient_id
A4: first_name
A5: last_name
A6: middle_name
A7: date_of_birth
A8: gender
A9: phone_number
A10: address
A11: Email Address
A12: Marital Status
... A31: Hepatitis B
A32: XYZ | B32: Postive, Negative
A33: XP02
A36: Consultation Feedback
A37: Diagonistics types | B37: Multiple checkbox | C37: QRMBA | D37: Iridiology
A38: Note | B38: Long Text
A40: Health Status
A41: Summary | B41: Long Text

Sheet Treatment&Therapy
A1: Treatment | F1: Diagonistics types | H1: Method Of treatment | J1: LIST OF TREATMENT RECEIVED | K1: =PROPER(J1) -> List Of Treatment Received
A2: patient_id | B2: Number | F2: Laboratory Test | H2: Nutritional Medicine | J2: Acutherapy(Ceragem)
A3: Patient Name | B3: first & Last name | F3: Iridiology Diagnosis | H3: Acupuncture/Acupressure Therapy | J3: Feet Massage
A4: Diagonistics types | B4: Multiple checkbox | F4: Sclerology Diagnosis | H4: Chiropractic Therapy | J4: Cns Massager (Central Nervous System)
A5: Note | B5: Long Text | F5: Qrmba | H5: Cupping Therapy(Dry, Wet And Fire) | J5: Chiropratic Gun Massage & ( Chiropractic Massage)
F6: Manual Diagnosis | H6: Aromatherapy | J6: Detoxification
A7: Health Status | F7: Reflexology Diagnosis | H7: Manual Therapy | J7: Ceragem Slimming Belt
A8: Summary | B8: Long Text | F8: Acupuncture Diagnosis | H8: Phytoremedies | J8: Aux Machine
H9: Nutritional Recipes | J9: Acupuncture
A10: Method Of treatment | B10: Multiple checkbox | J10: Reflexology/Manual Massage
J11: Cupping Therapy
J12: Turbo 8G Massage Machine
A13: List Of Treatment Required | B13: Multiple checkbox | J13: Head Heat Massage
J14: Knee Massage
J15: Shoulder Massage Machine
J16: Dds Bioenergy Massager
J17: Onions Broth Therapy
K20: =PROPER(J20)

Sheet Vitals
A1: Vitals
A2: Height (cm)
A3: Weight (Kg)
A4: Glucose Level (mg/dl)
A5: BP Systolic
A6: BP Diastolic
A7: BMI
A8: Hepatitis B | B8: Postive, Negative
A9: XYZ | B9: Postive, Negative
A10: XP02

Sheet APPOINTMENTS
A1: Appointment Dashboard
A2: appointment_id
A3: patient_id
A4: Patient_name
A5: appointment_date
A6: appointment_time
A7: reason_for_visit
A8: status

Sheet VISITS
A1: visit_id | B1: patient_id | C1: clinician_id | D1: visit_date | E1: complaint | F1: vital_signs | G1: diagnosis | H1: notes | I1: follow_up_date

Sheet DRUGS
A1: drug_id | B1: drug_name | C1: unit_price | D1: quantity_in_stock | E1: expiry_date | F1: stock_alert
B2: Liver Detox | F2: =IF(D2<10,"LOW","OK") -> LOW | I2: LIVER DETOX | J2: =PROPER(I2) -> Liver Detox
B3: Kidney Detox | F3: =IF(D3<10,"LOW","OK") -> LOW | I3: KIDNEY DETOX | J3: =PROPER(I3) -> Kidney Detox
B4: Anti-Viral | F4: =IF(D4<10,"LOW","OK") -> LOW | I4: ANTI-VIRAL | J4: =PROPER(I4) -> Anti-Viral
B5: Gbd(General Body Detox) | F5: =IF(D5<10,"LOW","OK") -> LOW | I5: GBD(GENERAL BODY DETOX) | J5: =PROPER(I5) -> Gbd(General Body Detox)
B6: Anti-Obstructive | F6: =IF(D6<10,"LOW","OK") -> LOW | I6: ANTI-OBSTRUCTIVE | J6: =PROPER(I6) -> Anti-Obstructive
B7: Immune Booster | F7: =IF(D7<10,"LOW","OK") -> LOW | I7: IMMUNE BOOSTER | J7: =PROPER(I7) -> Immune Booster
B8: Cardio-Solution | F8: =IF(D8<10,"LOW","OK") -> LOW | I8: CARDIO-SOLUTION | J8: =PROPER(I8) -> Cardio-Solution
B9: CNM | F9: =IF(D9<10,"LOW","OK") -> LOW | I9: CNM | J9: =PROPER(I9) -> Cnm
B10: CNS | F10: =IF(D10<10,"LOW","OK") -> LOW | I10: CNS | J10: =PROPER(I10) -> Cns
B11: Psa(Prostate Solution) | F11: =IF(D11<10,"LOW","OK") -> LOW | I11: PSA(PROSTATE SOLUTION) | J11: =PROPER(I11) -> Psa(Prostate Solution)
B12: Staph Cleanser | F12: =IF(D12<10,"LOW","OK") -> LOW | I12: STAPH CLEANSER | J12: =PROPER(I12) -> Staph Cleanser
B13: Clove Extract | F13: =IF(D13<10,"LOW","OK") -> LOW | I13: CLOVE EXTRACT | J13: =PROPER(I13) -> Clove Extract
... B19: Activated Charcoal | F19: =IF(D19<10,"LOW","OK") -> LOW | I19: ACTIVATED CHARCOAL | J19: =PROPER(I19) -> Activated Charcoal
F20: =IF(D20<10,"LOW","OK") -> LOW
F21: =IF(D21<10,"LOW","OK") -> LOW
F22: =IF(D22<10,"LOW","OK") -> LOW
F23: =IF(D23<10,"LOW","OK") -> LOW
F24: =IF(D24<10,"LOW","OK") -> LOW
F25: =IF(D25<10,"LOW","OK") -> LOW
F26: =IF(D26<10,"LOW","OK") -> LOW
F27: =IF(D27<10,"LOW","OK") -> LOW
F28: =IF(D28<10,"LOW","OK") -> LOW
F29: =IF(D29<10,"LOW","OK") -> LOW
F30: =IF(D30<10,"LOW","OK") -> LOW
F31: =IF(D31<10,"LOW","OK") -> LOW
... F999: =IF(D999<10,"LOW","OK") -> LOW

Sheet PRESCRIPTIONS
A1: prescription_id | B1: visit_id | C1: drug_id | D1: dosage | E1: quantity | F1: instructions | G1: date_prescribed

Sheet BILLING
A1: bill_id | B1: visit_id | C1: consultation_fee | D1: drug_cost | E1: total_amount | F1: amount_paid | G1: balance | H1: payment_status | I1: payment_date
E2: =C2+D2 -> 0 | G2: =E2-F2 -> 0
E3: =C3+D3 -> 0 | G3: =E3-F3 -> 0
E4: =C4+D4 -> 0 | G4: =E4-F4 -> 0
E5: =C5+D5 -> 0 | G5: =E5-F5 -> 0
E6: =C6+D6 -> 0 | G6: =E6-F6 -> 0
E7: =C7+D7 -> 0 | G7: =E7-F7 -> 0
E8: =C8+D8 -> 0 | G8: =E8-F8 -> 0
E9: =C9+D9 -> 0 | G9: =E9-F9 -> 0
E10: =C10+D10 -> 0 | G10: =E10-F10 -> 0
E11: =C11+D11 -> 0 | G11: =E11-F11 -> 0
E12: =C12+D12 -> 0 | G12: =E12-F12 -> 0
E13: =C13+D13 -> 0 | G13: =E13-F13 -> 0
... E999: =C999+D999 -> 0 | G999: =E999-F999 -> 0

Sheet DASHBOARD
A1: CLINIC DASHBOARD
A3: Total Registered Patients: | B3: =COUNTA(PATIENTS!A:A)-1 -> 35
A4: Total Visits: | B4: =COUNTA(VISITS!A:A)-1 -> 0
A5: Total Appointments: | B5: =COUNTA(APPOINTMENTS!A:A)-1 -> 7
A6: Total Revenue (Paid): | B6: =SUMIF(BILLING!H:H,"Paid",BILLING!F:F) -> 0
A7: Outstanding Balance: | B7: =SUM(BILLING!G:G) -> 0
A9: Drugs Low in Stock (<10 units):
A10: Drug Name | B10: Quantity

Sheet CHARTS

Sheet RECEIPT
A1: CLINIC PAYMENT RECEIPT
A3: Enter Bill ID:
A5: Visit ID: | B5: =IF($B$3="","",VLOOKUP($B$3,BILLING!A:I,2,FALSE))
A6: Consultation Fee: | B6: =IF($B$3="","",VLOOKUP($B$3,BILLING!A:I,3,FALSE))
A7: Drug Cost: | B7: =IF($B$3="","",VLOOKUP($B$3,BILLING!A:I,4,FALSE))
A8: Total Amount: | B8: =IF($B$3="","",VLOOKUP($B$3,BILLING!A:I,5,FALSE))
A9: Amount Paid: | B9: =IF($B$3="","",VLOOKUP($B$3,BILLING!A:I,6,FALSE))
A10: Balance: | B10: =IF($B$3="","",VLOOKUP($B$3,BILLING!A:I,7,FALSE))
A11: Payment Status: | B11: =IF($B$3="","",VLOOKUP($B$3,BILLING!A:I,8,FALSE))
A13: Thank you for your patronage.
